[["Map",1,2,62,63],"blog",["Map",3,4,28,29,48,49],"post-3",{"id":3,"data":5,"body":9,"filePath":10,"digest":11,"rendered":12},{"title":6,"description":7,"pubDate":8},"Hello, World","this is a post example",["Date","2023-01-21T00:00:00.000Z"],"# Hi there!\n\nThis Markdown file creates a page at `your-domain.com/blog/post1/`\n\nIt probably isn't styled much, but Markdown does support:\n\n- **bold** and _italics._\n- lists\n- [links](https://astro.build)\n- and more!","src/data/blog/post-3.md","7cee01fb1916a739",{"html":13,"metadata":14},"\u003Ch1 id=\"hi-there\">Hi there!\u003C/h1>\n\u003Cp>This Markdown file creates a page at \u003Ccode>your-domain.com/blog/post1/\u003C/code>\u003C/p>\n\u003Cp>It probably isn’t styled much, but Markdown does support:\u003C/p>\n\u003Cul>\n\u003Cli>\u003Cstrong>bold\u003C/strong> and \u003Cem>italics.\u003C/em>\u003C/li>\n\u003Cli>lists\u003C/li>\n\u003Cli>\u003Ca href=\"https://astro.build\">links\u003C/a>\u003C/li>\n\u003Cli>and more!\u003C/li>\n\u003C/ul>",{"headings":15,"localImagePaths":20,"remoteImagePaths":21,"frontmatter":22,"imagePaths":27},[16],{"depth":17,"slug":18,"text":19},1,"hi-there","Hi there!",[],[],{"title":6,"description":7,"pubDate":23,"category":24,"draft":25,"minutesRead":26},["Date","2023-01-21T00:00:00.000Z"],"intro",false,"1 min read",[],"post1",{"id":28,"data":30,"body":33,"filePath":34,"digest":35,"rendered":36},{"title":31,"description":31,"pubDate":32},"How I made 4.5 Millions at 24 years old",["Date","2024-03-26T00:00:00.000Z"],"# I didn't","src/data/blog/post1.md","6dab86312d0d31b0",{"html":37,"metadata":38},"\u003Ch1 id=\"i-didnt\">I didn’t\u003C/h1>",{"headings":39,"localImagePaths":43,"remoteImagePaths":44,"frontmatter":45,"imagePaths":47},[40],{"depth":17,"slug":41,"text":42},"i-didnt","I didn’t",[],[],{"title":31,"description":31,"pubDate":46,"category":24,"draft":25,"minutesRead":26},["Date","2024-03-26T00:00:00.000Z"],[],"post2",{"id":48,"data":50,"body":9,"filePath":52,"digest":11,"rendered":53},{"title":6,"description":7,"pubDate":51},["Date","2023-01-21T00:00:00.000Z"],"src/data/blog/post2.md",{"html":13,"metadata":54},{"headings":55,"localImagePaths":57,"remoteImagePaths":58,"frontmatter":59,"imagePaths":61},[56],{"depth":17,"slug":18,"text":19},[],[],{"title":6,"description":7,"pubDate":60,"category":24,"draft":25,"minutesRead":26},["Date","2023-01-21T00:00:00.000Z"],[],"meta::meta",["Map",64,65,66,67,68,69],"astro-config-digest","{\"root\":{},\"srcDir\":{},\"publicDir\":{},\"outDir\":{},\"cacheDir\":{},\"site\":\"https://zoeyai1221.github.io/zoeyai.github.io/\",\"compressHTML\":true,\"base\":\"/zoeyai.github.io\",\"trailingSlash\":\"ignore\",\"output\":\"static\",\"scopedStyleStrategy\":\"attribute\",\"build\":{\"format\":\"directory\",\"client\":{},\"server\":{},\"assets\":\"_astro\",\"serverEntry\":\"entry.mjs\",\"redirects\":true,\"inlineStylesheets\":\"auto\",\"concurrency\":1},\"server\":{\"open\":false,\"host\":false,\"port\":4321,\"streaming\":true,\"allowedHosts\":[]},\"redirects\":{},\"image\":{\"endpoint\":{\"route\":\"/_image\"},\"service\":{\"entrypoint\":\"astro/assets/services/sharp\",\"config\":{}},\"domains\":[],\"remotePatterns\":[],\"responsiveStyles\":false},\"devToolbar\":{\"enabled\":true},\"markdown\":{\"syntaxHighlight\":{\"type\":\"shiki\",\"excludeLangs\":[\"math\"]},\"shikiConfig\":{\"langs\":[],\"langAlias\":{},\"theme\":\"github-dark\",\"themes\":{},\"wrap\":false,\"transformers\":[]},\"remarkPlugins\":[null],\"rehypePlugins\":[],\"remarkRehype\":{},\"gfm\":true,\"smartypants\":{\"backticks\":true,\"closingQuotes\":{\"double\":\"”\",\"single\":\"’\"},\"dashes\":true,\"ellipses\":true,\"openingQuotes\":{\"double\":\"“\",\"single\":\"‘\"},\"quotes\":true}},\"security\":{\"checkOrigin\":true,\"allowedDomains\":[],\"csp\":false,\"actionBodySizeLimit\":1048576,\"serverIslandBodySizeLimit\":1048576},\"env\":{\"schema\":{},\"validateSecrets\":false},\"prerenderConflictBehavior\":\"warn\",\"fonts\":[{\"name\":\"CabinetGrotesk\",\"cssVariable\":\"--font-cabinet-grotesk\",\"provider\":{\"name\":\"local\"},\"options\":{\"variants\":[{\"weight\":\"100 1000\",\"style\":\"normal\",\"src\":[\"./src/assets/fonts/CabinetGrotesk-Variable.ttf\"]}]}},{\"name\":\"Satoshi\",\"cssVariable\":\"--font-satoshi\",\"provider\":{\"name\":\"local\"},\"options\":{\"variants\":[{\"weight\":\"100 1000\",\"style\":\"normal\",\"src\":[\"./src/assets/fonts/Satoshi-Variable.ttf\"]},{\"weight\":\"100 1000\",\"style\":\"italic\",\"src\":[\"./src/assets/fonts/Satoshi-VariableItalic.ttf\"]}]}}],\"experimental\":{\"clientPrerender\":false,\"contentIntellisense\":false,\"chromeDevtoolsWorkspace\":false,\"svgo\":true,\"rustCompiler\":false,\"queuedRendering\":{\"enabled\":false}},\"legacy\":{\"collectionsBackwardsCompat\":false}}","astro-version","6.1.3","content-config-digest","54a85a41418d47e5"]